<?xml version="1.0" encoding="UTF-8" ?>
<!DOCTYPE mapper PUBLIC "-//mybatis.org//DTD Mapper 3.0//EN" "http://mybatis.org/dtd/mybatis-3-mapper.dtd">

<mapper namespace="recruit">
  <select id="selectAll" resultType="recruitvo">
    <![CDATA[ SELECT * FROM recruit ]]>
  </select>

  <insert id="insert" parameterType="recruitvo">
    <![CDATA[ insert into recruit value(null, 'estsoft 2016 하반기 공채', now(), now(), 1); ]]>
    <selectKey keyProperty="id" resultType="int">
      SELECT LAST_INSERT_ID()
    </selectKey>
  </insert>

  <select id="selectById" resultType="recruitvo" parameterType="int">
    <![CDATA[  SELECT * FROM recruit WHERE id=#{id } ]]>
  </select>
</mapper>